xet/__init__.py
xet/__main__.py
xet/cli.py
xet/xet.py
xet-1.3.1.dist-info/LICENSE
xet-1.3.1.dist-info/METADATA
xet-1.3.1.dist-info/WHEEL
xet-1.3.1.dist-info/entry_points.txt
xet-1.3.1.dist-info/RECORD
