Metadata-Version: 2.3
Name: xet
Version: 1.3.1
Summary: CLI Tool for quickly updating values across your project/machine.
Author: Art
Requires-Python: >=3.10,<4.0
Classifier: Programming Language :: Python :: 3
Classifier: Programming Language :: Python :: 3.10
Classifier: Programming Language :: Python :: 3.11
Classifier: Programming Language :: Python :: 3.12
Classifier: Programming Language :: Python :: 3.13
Requires-Dist: argparse (>=1.4.0,<2.0.0)
Requires-Dist: colorama (>=0.4.6,<0.5.0)
Requires-Dist: diff-match-patch (==20241021)
Requires-Dist: fabric (>=3.2.2,<4.0.0)
